{
  "ticker": "472150",
  "stockName": "TIGER 배당커버드콜액티브",
  "stockEndType": "etf",
  "description": "- 이 ETF는 주로 국내 주식을 주된 투자대상자산으로 하며, 코스피 200 커버드콜 5% OTM 지수를 비교지수로 하여 ETF 순자산가치의 변화가 비교지수를 초과하도록 운용하는 것을 목표로 하는 ETF입니다. 이 ETF는 초과수익 실현을 위해 업종 내 배당 수익률 및 배당 성장률이 높은 종목(현금 배당뿐만 아니라 주식 배당 및 자사주 매입 포함)으로 주식 포트폴리오를 보유하면서 콜옵션을 매도하는 커버드콜 전략을 활용하여 주가하락 위험을 부분적으로 방어하고 콜옵션 매도에 따른 프리미엄을 확보합니다.<br>- ‘코스피 200 커버드콜 5% OTM 지수’는 한국거래소에서 코스피 200 지수와 코스피 200 옵션시장에 상장된 콜옵션종목을 이용하여 산출하는 지수입니다.",
  "issuerName": "미래에셋자산운용",
  "marketValue": "1조 4,020억",
  "totalNav": "1조 4,158억",
  "nav": "20,524.85",
  "totalFee": 0.5,
  "dividendYieldTtm": 15.24,
  "deviationSign": "-",
  "deviationRate": 0.24,
  "returnRate1m": 24.76,
  "returnRate3m": 33.36,
  "returnRate1y": 150.92,
  "totalInfos": [
    {
      "code": "lastClosePrice",
      "key": "전일",
      "value": "20,475"
    },
    {
      "code": "openPrice",
      "key": "시가",
      "value": "20,610",
      "compareToPreviousPrice": {
        "code": "2",
        "text": "상승",
        "name": "RISING"
      }
    },
    {
      "code": "highPrice",
      "key": "고가",
      "value": "20,730",
      "compareToPreviousPrice": {
        "code": "2",
        "text": "상승",
        "name": "RISING"
      }
    },
    {
      "code": "lowPrice",
      "key": "저가",
      "value": "20,280",
      "compareToPreviousPrice": {
        "code": "5",
        "text": "하락",
        "name": "FALLING"
      }
    },
    {
      "code": "accumulatedTradingVolume",
      "key": "거래량",
      "value": "2,819,073"
    },
    {
      "code": "accumulatedTradingValue",
      "key": "대금",
      "value": "57,853백만"
    },
    {
      "code": "highPriceOf52Weeks",
      "key": "52주 최고",
      "value": "21,045"
    },
    {
      "code": "highPriceOf52WeeksAdjusted",
      "key": "원주가 기준",
      "value": "21,045"
    },
    {
      "code": "lowPriceOf52Weeks",
      "key": "52주 최저",
      "value": "8,300"
    },
    {
      "code": "lowPriceOf52WeeksAdjusted",
      "key": "원주가 기준",
      "value": "10,070"
    },
    {
      "code": "oneMonthEarnRate",
      "key": "최근 1개월 수익률",
      "value": "+24.76%",
      "compareToPreviousPrice": {
        "code": "2",
        "text": "상승",
        "name": "RISING"
      }
    },
    {
      "code": "threeMonthEarnRate",
      "key": "최근 3개월 수익률",
      "value": "+33.36%",
      "compareToPreviousPrice": {
        "code": "2",
        "text": "상승",
        "name": "RISING"
      }
    },
    {
      "code": "sixMonthEarnRate",
      "key": "최근 6개월 수익률",
      "value": "+70.98%",
      "compareToPreviousPrice": {
        "code": "2",
        "text": "상승",
        "name": "RISING"
      }
    },
    {
      "code": "oneYearEarnRate",
      "key": "최근 1년 수익률",
      "value": "+150.92%",
      "compareToPreviousPrice": {
        "code": "2",
        "text": "상승",
        "name": "RISING"
      }
    },
    {
      "code": "nav",
      "key": "NAV",
      "value": "20,276.05"
    },
    {
      "code": "fundPay",
      "key": "펀드보수",
      "value": "0.5%"
    },
    {
      "code": "etfBaseIdx",
      "key": "기초지수",
      "value": "코스피 200 커버드콜 5% OTM 지수(PR 지수)"
    },
    {
      "code": "issueName",
      "key": "운용사",
      "value": "미래에셋자산운용"
    }
  ],
  "industryCompareInfo": [
    {
      "stockType": "domestic",
      "stockEndType": "stock",
      "itemCode": "069500",
      "reutersCode": "069500",
      "stockName": "KODEX 200",
      "sosok": "0",
      "closePrice": "99,905",
      "compareToPreviousClosePrice": "-1,140",
      "compareToPreviousPrice": {
        "code": "5",
        "text": "하락",
        "name": "FALLING"
      },
      "fluctuationsRatio": "-1.13",
      "accumulatedTradingVolume": "-",
      "accumulatedTradingValue": "-",
      "marketValue": "21,904,171",
      "nav": "0",
      "threeMonthEarningRate": "0",
      "stockExchangeType": {
        "code": "KS",
        "zoneId": "Asia/Seoul",
        "nationType": "KOR",
        "delayTime": 0,
        "startTime": "0900",
        "endTime": "1530",
        "closePriceSendTime": "1630",
        "nameKor": "코스피",
        "nameEng": "KOSPI",
        "stockType": "domestic",
        "nationCode": "KOR",
        "nationName": "대한민국",
        "name": "KOSPI"
      },
      "endUrl": "https://m.stock.naver.com/domestic/stock/069500"
    },
    {
      "stockType": "domestic",
      "stockEndType": "stock",
      "itemCode": "360750",
      "reutersCode": "360750",
      "stockName": "TIGER 미국S&P500",
      "sosok": "0",
      "closePrice": "26,160",
      "compareToPreviousClosePrice": "-55",
      "compareToPreviousPrice": {
        "code": "5",
        "text": "하락",
        "name": "FALLING"
      },
      "fluctuationsRatio": "-0.21",
      "accumulatedTradingVolume": "-",
      "accumulatedTradingValue": "-",
      "marketValue": "16,547,508",
      "nav": "0",
      "threeMonthEarningRate": "0",
      "stockExchangeType": {
        "code": "KS",
        "zoneId": "Asia/Seoul",
        "nationType": "KOR",
        "delayTime": 0,
        "startTime": "0900",
        "endTime": "1530",
        "closePriceSendTime": "1630",
        "nameKor": "코스피",
        "nameEng": "KOSPI",
        "stockType": "domestic",
        "nationCode": "KOR",
        "nationName": "대한민국",
        "name": "KOSPI"
      },
      "endUrl": "https://m.stock.naver.com/domestic/stock/360750"
    },
    {
      "stockType": "domestic",
      "stockEndType": "stock",
      "itemCode": "396500",
      "reutersCode": "396500",
      "stockName": "TIGER 반도체TOP10",
      "sosok": "0",
      "closePrice": "40,115",
      "compareToPreviousClosePrice": "-240",
      "compareToPreviousPrice": {
        "code": "5",
        "text": "하락",
        "name": "FALLING"
      },
      "fluctuationsRatio": "-0.59",
      "accumulatedTradingVolume": "-",
      "accumulatedTradingValue": "-",
      "marketValue": "10,365,716",
      "nav": "0",
      "threeMonthEarningRate": "0",
      "stockExchangeType": {
        "code": "KS",
        "zoneId": "Asia/Seoul",
        "nationType": "KOR",
        "delayTime": 0,
        "startTime": "0900",
        "endTime": "1530",
        "closePriceSendTime": "1630",
        "nameKor": "코스피",
        "nameEng": "KOSPI",
        "stockType": "domestic",
        "nationCode": "KOR",
        "nationName": "대한민국",
        "name": "KOSPI"
      },
      "endUrl": "https://m.stock.naver.com/domestic/stock/396500"
    },
    {
      "stockType": "domestic",
      "stockEndType": "stock",
      "itemCode": "133690",
      "reutersCode": "133690",
      "stockName": "TIGER 미국나스닥100",
      "sosok": "0",
      "closePrice": "177,990",
      "compareToPreviousClosePrice": "285",
      "compareToPreviousPrice": {
        "code": "2",
        "text": "상승",
        "name": "RISING"
      },
      "fluctuationsRatio": "0.16",
      "accumulatedTradingVolume": "-",
      "accumulatedTradingValue": "-",
      "marketValue": "9,223,441",
      "nav": "0",
      "threeMonthEarningRate": "0",
      "stockExchangeType": {
        "code": "KS",
        "zoneId": "Asia/Seoul",
        "nationType": "KOR",
        "delayTime": 0,
        "startTime": "0900",
        "endTime": "1530",
        "closePriceSendTime": "1630",
        "nameKor": "코스피",
        "nameEng": "KOSPI",
        "stockType": "domestic",
        "nationCode": "KOR",
        "nationName": "대한민국",
        "name": "KOSPI"
      },
      "endUrl": "https://m.stock.naver.com/domestic/stock/133690"
    },
    {
      "stockType": "domestic",
      "stockEndType": "stock",
      "itemCode": "102110",
      "reutersCode": "102110",
      "stockName": "TIGER 200",
      "sosok": "0",
      "closePrice": "99,970",
      "compareToPreviousClosePrice": "-1,005",
      "compareToPreviousPrice": {
        "code": "5",
        "text": "하락",
        "name": "FALLING"
      },
      "fluctuationsRatio": "-1.00",
      "accumulatedTradingVolume": "-",
      "accumulatedTradingValue": "-",
      "marketValue": "8,777,366",
      "nav": "0",
      "threeMonthEarningRate": "0",
      "stockExchangeType": {
        "code": "KS",
        "zoneId": "Asia/Seoul",
        "nationType": "KOR",
        "delayTime": 0,
        "startTime": "0900",
        "endTime": "1530",
        "closePriceSendTime": "1630",
        "nameKor": "코스피",
        "nameEng": "KOSPI",
        "stockType": "domestic",
        "nationCode": "KOR",
        "nationName": "대한민국",
        "name": "KOSPI"
      },
      "endUrl": "https://m.stock.naver.com/domestic/stock/102110"
    },
    {
      "stockType": "domestic",
      "stockEndType": "stock",
      "itemCode": "379800",
      "reutersCode": "379800",
      "stockName": "KODEX 미국S&P500",
      "sosok": "0",
      "closePrice": "23,870",
      "compareToPreviousClosePrice": "-15",
      "compareToPreviousPrice": {
        "code": "5",
        "text": "하락",
        "name": "FALLING"
      },
      "fluctuationsRatio": "-0.06",
      "accumulatedTradingVolume": "-",
      "accumulatedTradingValue": "-",
      "marketValue": "8,686,293",
      "nav": "0",
      "threeMonthEarningRate": "0",
      "stockExchangeType": {
        "code": "KS",
        "zoneId": "Asia/Seoul",
        "nationType": "KOR",
        "delayTime": 0,
        "startTime": "0900",
        "endTime": "1530",
        "closePriceSendTime": "1630",
        "nameKor": "코스피",
        "nameEng": "KOSPI",
        "stockType": "domestic",
        "nationCode": "KOR",
        "nationName": "대한민국",
        "name": "KOSPI"
      },
      "endUrl": "https://m.stock.naver.com/domestic/stock/379800"
    }
  ],
  "fetchedAt": "2026-05-03T22:20:08.680638"
}