{
  "ticker": "482730",
  "stockName": "TIGER 미국S&P500타겟데일리커버드콜",
  "stockEndType": "etf",
  "description": "- 이 ETF는 주로 주식을 주된 투자대상자산으로 하며, “S&P 500 10% Daily Premium Covered Call 지수(Total Return)(원화환산)”의 수익률 추종을 목적으로 하는 ETF입니다. 이 ETF는 해외 주식에 투자하면서도 환헤지를 하지 않으므로 기초지수의 원화환산 수익률에 연동하게 됩니다.<br>- “S&P 500 10% Daily Premium Covered Call 지수(Total Return)(원화환산)”는 S&P Total Market 지수 종목 중 조건을 만족하는 시가총액 상위 500개 기업을 구성종목으로 하며 연 간 프리미엄 10%을 목표로, 익일 만기하는 S&P500 ATM 옵션을 매 영업일 매도하는 전략 지수 입니다.",
  "issuerName": "미래에셋자산운용",
  "marketValue": "5,856억",
  "totalNav": "5,883억",
  "nav": "12,104.31",
  "totalFee": 0.25,
  "dividendYieldTtm": 9.47,
  "deviationSign": "+",
  "deviationRate": 0.13,
  "returnRate1m": 6.92,
  "returnRate3m": 6.24,
  "returnRate1y": 32.84,
  "totalInfos": [
    {
      "code": "lastClosePrice",
      "key": "전일",
      "value": "12,120"
    },
    {
      "code": "openPrice",
      "key": "시가",
      "value": "12,185",
      "compareToPreviousPrice": {
        "code": "2",
        "text": "상승",
        "name": "RISING"
      }
    },
    {
      "code": "highPrice",
      "key": "고가",
      "value": "12,210",
      "compareToPreviousPrice": {
        "code": "2",
        "text": "상승",
        "name": "RISING"
      }
    },
    {
      "code": "lowPrice",
      "key": "저가",
      "value": "12,050",
      "compareToPreviousPrice": {
        "code": "5",
        "text": "하락",
        "name": "FALLING"
      }
    },
    {
      "code": "accumulatedTradingVolume",
      "key": "거래량",
      "value": "735,719"
    },
    {
      "code": "accumulatedTradingValue",
      "key": "대금",
      "value": "8,918백만"
    },
    {
      "code": "highPriceOf52Weeks",
      "key": "52주 최고",
      "value": "12,230"
    },
    {
      "code": "highPriceOf52WeeksAdjusted",
      "key": "원주가 기준",
      "value": "12,230"
    },
    {
      "code": "lowPriceOf52Weeks",
      "key": "52주 최저",
      "value": "9,017"
    },
    {
      "code": "lowPriceOf52WeeksAdjusted",
      "key": "원주가 기준",
      "value": "9,875"
    },
    {
      "code": "oneMonthEarnRate",
      "key": "최근 1개월 수익률",
      "value": "+6.92%",
      "compareToPreviousPrice": {
        "code": "2",
        "text": "상승",
        "name": "RISING"
      }
    },
    {
      "code": "threeMonthEarnRate",
      "key": "최근 3개월 수익률",
      "value": "+6.24%",
      "compareToPreviousPrice": {
        "code": "2",
        "text": "상승",
        "name": "RISING"
      }
    },
    {
      "code": "sixMonthEarnRate",
      "key": "최근 6개월 수익률",
      "value": "+6.97%",
      "compareToPreviousPrice": {
        "code": "2",
        "text": "상승",
        "name": "RISING"
      }
    },
    {
      "code": "oneYearEarnRate",
      "key": "최근 1년 수익률",
      "value": "+32.84%",
      "compareToPreviousPrice": {
        "code": "2",
        "text": "상승",
        "name": "RISING"
      }
    },
    {
      "code": "nav",
      "key": "NAV",
      "value": "12,155.38"
    },
    {
      "code": "fundPay",
      "key": "펀드보수",
      "value": "0.25%"
    },
    {
      "code": "etfBaseIdx",
      "key": "기초지수",
      "value": "S&P500 10% Daily Premium Covered Call Index(TR)"
    },
    {
      "code": "issueName",
      "key": "운용사",
      "value": "미래에셋자산운용"
    }
  ],
  "industryCompareInfo": [
    {
      "stockType": "domestic",
      "stockEndType": "stock",
      "itemCode": "069500",
      "reutersCode": "069500",
      "stockName": "KODEX 200",
      "sosok": "0",
      "closePrice": "99,905",
      "compareToPreviousClosePrice": "-1,140",
      "compareToPreviousPrice": {
        "code": "5",
        "text": "하락",
        "name": "FALLING"
      },
      "fluctuationsRatio": "-1.13",
      "accumulatedTradingVolume": "-",
      "accumulatedTradingValue": "-",
      "marketValue": "21,904,171",
      "nav": "0",
      "threeMonthEarningRate": "0",
      "stockExchangeType": {
        "code": "KS",
        "zoneId": "Asia/Seoul",
        "nationType": "KOR",
        "delayTime": 0,
        "startTime": "0900",
        "endTime": "1530",
        "closePriceSendTime": "1630",
        "nameKor": "코스피",
        "nameEng": "KOSPI",
        "stockType": "domestic",
        "nationCode": "KOR",
        "nationName": "대한민국",
        "name": "KOSPI"
      },
      "endUrl": "https://m.stock.naver.com/domestic/stock/069500"
    },
    {
      "stockType": "domestic",
      "stockEndType": "stock",
      "itemCode": "360750",
      "reutersCode": "360750",
      "stockName": "TIGER 미국S&P500",
      "sosok": "0",
      "closePrice": "26,160",
      "compareToPreviousClosePrice": "-55",
      "compareToPreviousPrice": {
        "code": "5",
        "text": "하락",
        "name": "FALLING"
      },
      "fluctuationsRatio": "-0.21",
      "accumulatedTradingVolume": "-",
      "accumulatedTradingValue": "-",
      "marketValue": "16,547,508",
      "nav": "0",
      "threeMonthEarningRate": "0",
      "stockExchangeType": {
        "code": "KS",
        "zoneId": "Asia/Seoul",
        "nationType": "KOR",
        "delayTime": 0,
        "startTime": "0900",
        "endTime": "1530",
        "closePriceSendTime": "1630",
        "nameKor": "코스피",
        "nameEng": "KOSPI",
        "stockType": "domestic",
        "nationCode": "KOR",
        "nationName": "대한민국",
        "name": "KOSPI"
      },
      "endUrl": "https://m.stock.naver.com/domestic/stock/360750"
    },
    {
      "stockType": "domestic",
      "stockEndType": "stock",
      "itemCode": "396500",
      "reutersCode": "396500",
      "stockName": "TIGER 반도체TOP10",
      "sosok": "0",
      "closePrice": "40,115",
      "compareToPreviousClosePrice": "-240",
      "compareToPreviousPrice": {
        "code": "5",
        "text": "하락",
        "name": "FALLING"
      },
      "fluctuationsRatio": "-0.59",
      "accumulatedTradingVolume": "-",
      "accumulatedTradingValue": "-",
      "marketValue": "10,365,716",
      "nav": "0",
      "threeMonthEarningRate": "0",
      "stockExchangeType": {
        "code": "KS",
        "zoneId": "Asia/Seoul",
        "nationType": "KOR",
        "delayTime": 0,
        "startTime": "0900",
        "endTime": "1530",
        "closePriceSendTime": "1630",
        "nameKor": "코스피",
        "nameEng": "KOSPI",
        "stockType": "domestic",
        "nationCode": "KOR",
        "nationName": "대한민국",
        "name": "KOSPI"
      },
      "endUrl": "https://m.stock.naver.com/domestic/stock/396500"
    },
    {
      "stockType": "domestic",
      "stockEndType": "stock",
      "itemCode": "133690",
      "reutersCode": "133690",
      "stockName": "TIGER 미국나스닥100",
      "sosok": "0",
      "closePrice": "177,990",
      "compareToPreviousClosePrice": "285",
      "compareToPreviousPrice": {
        "code": "2",
        "text": "상승",
        "name": "RISING"
      },
      "fluctuationsRatio": "0.16",
      "accumulatedTradingVolume": "-",
      "accumulatedTradingValue": "-",
      "marketValue": "9,223,441",
      "nav": "0",
      "threeMonthEarningRate": "0",
      "stockExchangeType": {
        "code": "KS",
        "zoneId": "Asia/Seoul",
        "nationType": "KOR",
        "delayTime": 0,
        "startTime": "0900",
        "endTime": "1530",
        "closePriceSendTime": "1630",
        "nameKor": "코스피",
        "nameEng": "KOSPI",
        "stockType": "domestic",
        "nationCode": "KOR",
        "nationName": "대한민국",
        "name": "KOSPI"
      },
      "endUrl": "https://m.stock.naver.com/domestic/stock/133690"
    },
    {
      "stockType": "domestic",
      "stockEndType": "stock",
      "itemCode": "102110",
      "reutersCode": "102110",
      "stockName": "TIGER 200",
      "sosok": "0",
      "closePrice": "99,970",
      "compareToPreviousClosePrice": "-1,005",
      "compareToPreviousPrice": {
        "code": "5",
        "text": "하락",
        "name": "FALLING"
      },
      "fluctuationsRatio": "-1.00",
      "accumulatedTradingVolume": "-",
      "accumulatedTradingValue": "-",
      "marketValue": "8,777,366",
      "nav": "0",
      "threeMonthEarningRate": "0",
      "stockExchangeType": {
        "code": "KS",
        "zoneId": "Asia/Seoul",
        "nationType": "KOR",
        "delayTime": 0,
        "startTime": "0900",
        "endTime": "1530",
        "closePriceSendTime": "1630",
        "nameKor": "코스피",
        "nameEng": "KOSPI",
        "stockType": "domestic",
        "nationCode": "KOR",
        "nationName": "대한민국",
        "name": "KOSPI"
      },
      "endUrl": "https://m.stock.naver.com/domestic/stock/102110"
    },
    {
      "stockType": "domestic",
      "stockEndType": "stock",
      "itemCode": "379800",
      "reutersCode": "379800",
      "stockName": "KODEX 미국S&P500",
      "sosok": "0",
      "closePrice": "23,870",
      "compareToPreviousClosePrice": "-15",
      "compareToPreviousPrice": {
        "code": "5",
        "text": "하락",
        "name": "FALLING"
      },
      "fluctuationsRatio": "-0.06",
      "accumulatedTradingVolume": "-",
      "accumulatedTradingValue": "-",
      "marketValue": "8,686,293",
      "nav": "0",
      "threeMonthEarningRate": "0",
      "stockExchangeType": {
        "code": "KS",
        "zoneId": "Asia/Seoul",
        "nationType": "KOR",
        "delayTime": 0,
        "startTime": "0900",
        "endTime": "1530",
        "closePriceSendTime": "1630",
        "nameKor": "코스피",
        "nameEng": "KOSPI",
        "stockType": "domestic",
        "nationCode": "KOR",
        "nationName": "대한민국",
        "name": "KOSPI"
      },
      "endUrl": "https://m.stock.naver.com/domestic/stock/379800"
    }
  ],
  "fetchedAt": "2026-05-03T22:21:51.262721"
}